{
    "Summer": {
        "termStart": "03/01/2022"
    },
    "T1": {
        "termStart": "14/02/2022",
        "K-D16-G03": {
            "name": "Goldstein G03",
            "2": {
                "Tue": [
                    {
                        "start": "10:30",
                        "end": "12:00"
                    },
                    {
                        "start": "12:00",
                        "end": "13:30"
                    }
                ]
            },
            "3": {
                "Tue": [
                    {
                        "start": "10:30",
                        "end": "12:00"
                    },
                    {
                        "start": "12:00",
                        "end": "13:30"
                    }
                ]
            },
            "4": {
                "Tue": [
                    {
                        "start": "10:30",
                        "end": "12:00"
                    },
                    {
                        "start": "12:00",
                        "end": "13:30"
                    }
                ]
            },
            "5": {
                "Tue": [
                    {
                        "start": "10:30",
                        "end": "12:00"
                    },
                    {
                        "start": "12:00",
                        "end": "13:30"
                    }
                ]
            },
            "7": {
                "Tue": [
                    {
                        "start": "10:30",
                        "end": "12:00"
                    },
                    {
                        "start": "12:00",
                        "end": "13:30"
                    }
                ]
            },
            "8": {
                "Tue": [
                    {
                        "start": "10:30",
                        "end": "12:00"
                    },
                    {
                        "start": "12:00",
                        "end": "13:30"
                    }
                ]
            },
            "9": {
                "Tue": [
                    {
                        "start": "10:30",
                        "end": "12:00"
                    },
                    {
                        "start": "12:00",
                        "end": "13:30"
                    }
                ]
            },
            "10": {
                "Tue": [
                    {
                        "start": "10:30",
                        "end": "12:00"
                    },
                    {
                        "start": "12:00",
                        "end": "13:30"
                    }
                ]
            }
        },
        "K-E15-G026": {
            "name": "Quadrangle G026",
            "2": {
                "Wed": [
                    {
                        "start": "10:30",
                        "end": "12:00"
                    }
                ]
            },
            "3": {
                "Wed": [
                    {
                        "start": "10:30",
                        "end": "12:00"
                    }
                ]
            },
            "4": {
                "Wed": [
                    {
                        "start": "10:30",
                        "end": "12:00"
                    }
                ]
            },
            "5": {
                "Wed": [
                    {
                        "start": "10:30",
                        "end": "12:00"
                    }
                ]
            },
            "7": {
                "Wed": [
                    {
                        "start": "10:30",
                        "end": "12:00"
                    }
                ]
            },
            "8": {
                "Wed": [
                    {
                        "start": "10:30",
                        "end": "12:00"
                    }
                ]
            },
            "9": {
                "Wed": [
                    {
                        "start": "10:30",
                        "end": "12:00"
                    }
                ]
            },
            "10": {
                "Wed": [
                    {
                        "start": "10:30",
                        "end": "12:00"
                    }
                ]
            }
        },
        "K-E15-G040": {
            "name": "Quadrangle G040",
            "2": {
                "Wed": [
                    {
                        "start": "12:00",
                        "end": "13:30"
                    }
                ],
                "Tue": [
                    {
                        "start": "13:00",
                        "end": "16:00"
                    }
                ]
            },
            "3": {
                "Wed": [
                    {
                        "start": "12:00",
                        "end": "13:30"
                    }
                ],
                "Tue": [
                    {
                        "start": "13:00",
                        "end": "16:00"
                    }
                ]
            },
            "4": {
                "Wed": [
                    {
                        "start": "12:00",
                        "end": "13:30"
                    }
                ],
                "Tue": [
                    {
                        "start": "13:00",
                        "end": "16:00"
                    }
                ]
            },
            "5": {
                "Wed": [
                    {
                        "start": "12:00",
                        "end": "13:30"
                    }
                ],
                "Tue": [
                    {
                        "start": "13:00",
                        "end": "16:00"
                    }
                ]
            },
            "7": {
                "Wed": [
                    {
                        "start": "12:00",
                        "end": "13:30"
                    }
                ],
                "Tue": [
                    {
                        "start": "13:00",
                        "end": "16:00"
                    }
                ]
            },
            "8": {
                "Wed": [
                    {
                        "start": "12:00",
                        "end": "13:30"
                    }
                ],
                "Tue": [
                    {
                        "start": "13:00",
                        "end": "16:00"
                    }
                ]
            },
            "9": {
                "Wed": [
                    {
                        "start": "12:00",
                        "end": "13:30"
                    }
                ],
                "Tue": [
                    {
                        "start": "13:00",
                        "end": "16:00"
                    }
                ]
            },
            "10": {
                "Wed": [
                    {
                        "start": "12:00",
                        "end": "13:30"
                    }
                ],
                "Tue": [
                    {
                        "start": "13:00",
                        "end": "16:00"
                    }
                ]
            },
            "1": {
                "Tue": [
                    {
                        "start": "13:00",
                        "end": "16:00"
                    }
                ]
            }
        },
        "K-E12-215": {
            "name": "UNSW Business School  215",
            "1": {
                "Thu": [
                    {
                        "start": "10:30",
                        "end": "12:00"
                    },
                    {
                        "start": "12:00",
                        "end": "13:30"
                    },
                    {
                        "start": "14:00",
                        "end": "15:30"
                    }
                ]
            },
            "2": {
                "Thu": [
                    {
                        "start": "10:30",
                        "end": "12:00"
                    },
                    {
                        "start": "12:00",
                        "end": "13:30"
                    },
                    {
                        "start": "14:00",
                        "end": "15:30"
                    }
                ]
            },
            "3": {
                "Thu": [
                    {
                        "start": "10:30",
                        "end": "12:00"
                    },
                    {
                        "start": "12:00",
                        "end": "13:30"
                    },
                    {
                        "start": "14:00",
                        "end": "15:30"
                    }
                ]
            },
            "4": {
                "Thu": [
                    {
                        "start": "10:30",
                        "end": "12:00"
                    },
                    {
                        "start": "12:00",
                        "end": "13:30"
                    },
                    {
                        "start": "14:00",
                        "end": "15:30"
                    }
                ]
            },
            "5": {
                "Thu": [
                    {
                        "start": "10:30",
                        "end": "12:00"
                    },
                    {
                        "start": "12:00",
                        "end": "13:30"
                    },
                    {
                        "start": "14:00",
                        "end": "15:30"
                    }
                ]
            },
            "7": {
                "Thu": [
                    {
                        "start": "10:30",
                        "end": "12:00"
                    },
                    {
                        "start": "12:00",
                        "end": "13:30"
                    },
                    {
                        "start": "14:00",
                        "end": "15:30"
                    }
                ]
            },
            "8": {
                "Thu": [
                    {
                        "start": "10:30",
                        "end": "12:00"
                    },
                    {
                        "start": "12:00",
                        "end": "13:30"
                    },
                    {
                        "start": "14:00",
                        "end": "15:30"
                    }
                ]
            },
            "9": {
                "Thu": [
                    {
                        "start": "10:30",
                        "end": "12:00"
                    },
                    {
                        "start": "12:00",
                        "end": "13:30"
                    },
                    {
                        "start": "14:00",
                        "end": "15:30"
                    }
                ]
            },
            "10": {
                "Thu": [
                    {
                        "start": "10:30",
                        "end": "12:00"
                    },
                    {
                        "start": "12:00",
                        "end": "13:30"
                    },
                    {
                        "start": "14:00",
                        "end": "15:30"
                    }
                ]
            }
        },
        "K-G17-G04": {
            "name": "Electrical Engineering G04",
            "1": {
                "Tue": [
                    {
                        "start": "09:00",
                        "end": "10:30"
                    },
                    {
                        "start": "10:30",
                        "end": "12:00"
                    },
                    {
                        "start": "13:00",
                        "end": "16:00"
                    }
                ]
            },
            "2": {
                "Tue": [
                    {
                        "start": "09:00",
                        "end": "10:30"
                    },
                    {
                        "start": "10:30",
                        "end": "12:00"
                    },
                    {
                        "start": "13:00",
                        "end": "16:00"
                    }
                ]
            },
            "3": {
                "Tue": [
                    {
                        "start": "09:00",
                        "end": "10:30"
                    },
                    {
                        "start": "10:30",
                        "end": "12:00"
                    },
                    {
                        "start": "13:00",
                        "end": "16:00"
                    }
                ]
            },
            "4": {
                "Tue": [
                    {
                        "start": "09:00",
                        "end": "10:30"
                    },
                    {
                        "start": "10:30",
                        "end": "12:00"
                    },
                    {
                        "start": "13:00",
                        "end": "16:00"
                    }
                ]
            },
            "5": {
                "Tue": [
                    {
                        "start": "09:00",
                        "end": "10:30"
                    },
                    {
                        "start": "10:30",
                        "end": "12:00"
                    },
                    {
                        "start": "13:00",
                        "end": "16:00"
                    }
                ]
            },
            "7": {
                "Tue": [
                    {
                        "start": "09:00",
                        "end": "10:30"
                    },
                    {
                        "start": "10:30",
                        "end": "12:00"
                    },
                    {
                        "start": "13:00",
                        "end": "16:00"
                    }
                ]
            },
            "8": {
                "Tue": [
                    {
                        "start": "09:00",
                        "end": "10:30"
                    },
                    {
                        "start": "10:30",
                        "end": "12:00"
                    },
                    {
                        "start": "13:00",
                        "end": "16:00"
                    }
                ]
            },
            "9": {
                "Tue": [
                    {
                        "start": "09:00",
                        "end": "10:30"
                    },
                    {
                        "start": "10:30",
                        "end": "12:00"
                    },
                    {
                        "start": "13:00",
                        "end": "16:00"
                    }
                ]
            },
            "10": {
                "Tue": [
                    {
                        "start": "09:00",
                        "end": "10:30"
                    },
                    {
                        "start": "10:30",
                        "end": "12:00"
                    },
                    {
                        "start": "13:00",
                        "end": "16:00"
                    }
                ]
            },
            "6": {
                "Tue": [
                    {
                        "start": "13:00",
                        "end": "16:00"
                    }
                ]
            }
        },
        "K-F23-228": {
            "name": "Mathews 228",
            "1": {
                "Tue": [
                    {
                        "start": "13:00",
                        "end": "14:30"
                    }
                ]
            },
            "2": {
                "Tue": [
                    {
                        "start": "13:00",
                        "end": "14:30"
                    }
                ]
            },
            "3": {
                "Tue": [
                    {
                        "start": "13:00",
                        "end": "14:30"
                    }
                ]
            },
            "4": {
                "Tue": [
                    {
                        "start": "13:00",
                        "end": "14:30"
                    }
                ]
            },
            "5": {
                "Tue": [
                    {
                        "start": "13:00",
                        "end": "14:30"
                    }
                ]
            },
            "7": {
                "Tue": [
                    {
                        "start": "13:00",
                        "end": "14:30"
                    }
                ]
            },
            "8": {
                "Tue": [
                    {
                        "start": "13:00",
                        "end": "14:30"
                    }
                ]
            },
            "9": {
                "Tue": [
                    {
                        "start": "13:00",
                        "end": "14:30"
                    }
                ]
            },
            "10": {
                "Tue": [
                    {
                        "start": "13:00",
                        "end": "14:30"
                    }
                ]
            }
        },
        "K-F23-105": {
            "name": "Mathews 105",
            "2": {
                "Tue": [
                    {
                        "start": "13:30",
                        "end": "15:00"
                    },
                    {
                        "start": "15:00",
                        "end": "18:00"
                    }
                ]
            },
            "3": {
                "Tue": [
                    {
                        "start": "13:30",
                        "end": "15:00"
                    },
                    {
                        "start": "15:00",
                        "end": "18:00"
                    }
                ]
            },
            "4": {
                "Tue": [
                    {
                        "start": "13:30",
                        "end": "15:00"
                    },
                    {
                        "start": "15:00",
                        "end": "18:00"
                    }
                ]
            },
            "5": {
                "Tue": [
                    {
                        "start": "13:30",
                        "end": "15:00"
                    },
                    {
                        "start": "15:00",
                        "end": "18:00"
                    }
                ]
            },
            "7": {
                "Tue": [
                    {
                        "start": "13:30",
                        "end": "15:00"
                    },
                    {
                        "start": "15:00",
                        "end": "18:00"
                    }
                ]
            },
            "8": {
                "Tue": [
                    {
                        "start": "13:30",
                        "end": "15:00"
                    },
                    {
                        "start": "15:00",
                        "end": "18:00"
                    }
                ]
            },
            "9": {
                "Tue": [
                    {
                        "start": "13:30",
                        "end": "15:00"
                    },
                    {
                        "start": "15:00",
                        "end": "18:00"
                    }
                ]
            },
            "10": {
                "Tue": [
                    {
                        "start": "13:30",
                        "end": "15:00"
                    },
                    {
                        "start": "15:00",
                        "end": "18:00"
                    }
                ]
            },
            "1": {
                "Tue": [
                    {
                        "start": "15:00",
                        "end": "18:00"
                    }
                ]
            },
            "6": {
                "Tue": [
                    {
                        "start": "15:00",
                        "end": "18:00"
                    }
                ]
            }
        },
        "K-D16-G09": {
            "name": "Goldstein G09",
            "2": {
                "Tue": [
                    {
                        "start": "16:30",
                        "end": "18:00"
                    }
                ]
            },
            "3": {
                "Tue": [
                    {
                        "start": "16:30",
                        "end": "18:00"
                    }
                ]
            },
            "4": {
                "Tue": [
                    {
                        "start": "16:30",
                        "end": "18:00"
                    }
                ]
            },
            "5": {
                "Tue": [
                    {
                        "start": "16:30",
                        "end": "18:00"
                    }
                ]
            },
            "7": {
                "Tue": [
                    {
                        "start": "16:30",
                        "end": "18:00"
                    }
                ]
            },
            "8": {
                "Tue": [
                    {
                        "start": "16:30",
                        "end": "18:00"
                    }
                ]
            },
            "9": {
                "Tue": [
                    {
                        "start": "16:30",
                        "end": "18:00"
                    }
                ]
            },
            "10": {
                "Tue": [
                    {
                        "start": "16:30",
                        "end": "18:00"
                    }
                ]
            }
        },
        "K-E12-G24": {
            "name": "UNSW Business School G24",
            "1": {
                "Thu": [
                    {
                        "start": "13:00",
                        "end": "16:00"
                    }
                ]
            },
            "2": {
                "Thu": [
                    {
                        "start": "13:00",
                        "end": "16:00"
                    }
                ]
            },
            "3": {
                "Thu": [
                    {
                        "start": "13:00",
                        "end": "16:00"
                    }
                ]
            },
            "4": {
                "Thu": [
                    {
                        "start": "13:00",
                        "end": "16:00"
                    }
                ]
            },
            "5": {
                "Thu": [
                    {
                        "start": "13:00",
                        "end": "16:00"
                    }
                ]
            }
        },
        "K-E15-G034": {
            "name": "Quadrangle G034",
            "1": {
                "Wed": [
                    {
                        "start": "10:00",
                        "end": "13:00"
                    }
                ]
            },
            "2": {
                "Wed": [
                    {
                        "start": "10:00",
                        "end": "13:00"
                    }
                ]
            },
            "3": {
                "Wed": [
                    {
                        "start": "10:00",
                        "end": "13:00"
                    }
                ]
            },
            "4": {
                "Wed": [
                    {
                        "start": "10:00",
                        "end": "13:00"
                    }
                ]
            },
            "5": {
                "Wed": [
                    {
                        "start": "10:00",
                        "end": "13:00"
                    }
                ]
            },
            "7": {
                "Wed": [
                    {
                        "start": "10:00",
                        "end": "13:00"
                    }
                ]
            },
            "8": {
                "Wed": [
                    {
                        "start": "10:00",
                        "end": "13:00"
                    }
                ]
            },
            "9": {
                "Wed": [
                    {
                        "start": "10:00",
                        "end": "13:00"
                    }
                ]
            },
            "10": {
                "Wed": [
                    {
                        "start": "10:00",
                        "end": "13:00"
                    }
                ]
            }
        },
        "K-E15-G053": {
            "name": "Quadrangle G053",
            "1": {
                "Tue": [
                    {
                        "start": "09:00",
                        "end": "12:00"
                    }
                ]
            },
            "2": {
                "Tue": [
                    {
                        "start": "09:00",
                        "end": "12:00"
                    }
                ]
            },
            "3": {
                "Tue": [
                    {
                        "start": "09:00",
                        "end": "12:00"
                    }
                ]
            },
            "4": {
                "Tue": [
                    {
                        "start": "09:00",
                        "end": "12:00"
                    }
                ]
            },
            "5": {
                "Tue": [
                    {
                        "start": "09:00",
                        "end": "12:00"
                    }
                ]
            },
            "7": {
                "Tue": [
                    {
                        "start": "09:00",
                        "end": "12:00"
                    }
                ]
            },
            "8": {
                "Tue": [
                    {
                        "start": "09:00",
                        "end": "12:00"
                    }
                ]
            },
            "9": {
                "Tue": [
                    {
                        "start": "09:00",
                        "end": "12:00"
                    }
                ]
            },
            "10": {
                "Tue": [
                    {
                        "start": "09:00",
                        "end": "12:00"
                    }
                ]
            }
        },
        "K-E15-1043": {
            "name": "Quadrangle 1043",
            "1": {
                "Wed": [
                    {
                        "start": "13:00",
                        "end": "16:00"
                    }
                ]
            },
            "2": {
                "Wed": [
                    {
                        "start": "13:00",
                        "end": "16:00"
                    }
                ]
            },
            "3": {
                "Wed": [
                    {
                        "start": "13:00",
                        "end": "16:00"
                    }
                ]
            },
            "4": {
                "Wed": [
                    {
                        "start": "13:00",
                        "end": "16:00"
                    }
                ]
            },
            "5": {
                "Wed": [
                    {
                        "start": "13:00",
                        "end": "16:00"
                    }
                ]
            },
            "7": {
                "Wed": [
                    {
                        "start": "13:00",
                        "end": "16:00"
                    }
                ]
            },
            "8": {
                "Wed": [
                    {
                        "start": "13:00",
                        "end": "16:00"
                    }
                ]
            },
            "9": {
                "Wed": [
                    {
                        "start": "13:00",
                        "end": "16:00"
                    }
                ]
            },
            "10": {
                "Wed": [
                    {
                        "start": "13:00",
                        "end": "16:00"
                    }
                ]
            }
        },
        "K-F23-101": {
            "name": "Mathews 101",
            "1": {
                "Wed": [
                    {
                        "start": "13:00",
                        "end": "16:00"
                    }
                ]
            },
            "2": {
                "Wed": [
                    {
                        "start": "13:00",
                        "end": "16:00"
                    }
                ]
            },
            "3": {
                "Wed": [
                    {
                        "start": "13:00",
                        "end": "16:00"
                    }
                ]
            },
            "4": {
                "Wed": [
                    {
                        "start": "13:00",
                        "end": "16:00"
                    }
                ]
            },
            "5": {
                "Wed": [
                    {
                        "start": "13:00",
                        "end": "16:00"
                    }
                ]
            },
            "6": {
                "Wed": [
                    {
                        "start": "13:00",
                        "end": "16:00"
                    }
                ]
            },
            "7": {
                "Wed": [
                    {
                        "start": "13:00",
                        "end": "16:00"
                    }
                ]
            },
            "8": {
                "Wed": [
                    {
                        "start": "13:00",
                        "end": "16:00"
                    }
                ]
            },
            "9": {
                "Wed": [
                    {
                        "start": "13:00",
                        "end": "16:00"
                    }
                ]
            },
            "10": {
                "Wed": [
                    {
                        "start": "13:00",
                        "end": "16:00"
                    }
                ]
            }
        },
        "K-E12-G26": {
            "name": "UNSW Business School  G26",
            "1": {
                "Wed": [
                    {
                        "start": "14:00",
                        "end": "17:00"
                    }
                ],
                "Tue": [
                    {
                        "start": "18:00",
                        "end": "21:00"
                    }
                ]
            },
            "2": {
                "Wed": [
                    {
                        "start": "14:00",
                        "end": "17:00"
                    }
                ],
                "Tue": [
                    {
                        "start": "18:00",
                        "end": "21:00"
                    }
                ]
            },
            "3": {
                "Wed": [
                    {
                        "start": "14:00",
                        "end": "17:00"
                    }
                ],
                "Tue": [
                    {
                        "start": "18:00",
                        "end": "21:00"
                    }
                ]
            },
            "4": {
                "Wed": [
                    {
                        "start": "14:00",
                        "end": "17:00"
                    }
                ],
                "Tue": [
                    {
                        "start": "18:00",
                        "end": "21:00"
                    }
                ]
            },
            "5": {
                "Wed": [
                    {
                        "start": "14:00",
                        "end": "17:00"
                    }
                ],
                "Tue": [
                    {
                        "start": "18:00",
                        "end": "21:00"
                    }
                ]
            },
            "6": {
                "Wed": [
                    {
                        "start": "14:00",
                        "end": "17:00"
                    }
                ],
                "Tue": [
                    {
                        "start": "18:00",
                        "end": "21:00"
                    }
                ]
            },
            "7": {
                "Wed": [
                    {
                        "start": "14:00",
                        "end": "17:00"
                    }
                ],
                "Tue": [
                    {
                        "start": "18:00",
                        "end": "21:00"
                    }
                ]
            },
            "8": {
                "Wed": [
                    {
                        "start": "14:00",
                        "end": "17:00"
                    }
                ],
                "Tue": [
                    {
                        "start": "18:00",
                        "end": "21:00"
                    }
                ]
            },
            "9": {
                "Wed": [
                    {
                        "start": "14:00",
                        "end": "17:00"
                    }
                ],
                "Tue": [
                    {
                        "start": "18:00",
                        "end": "21:00"
                    }
                ]
            },
            "10": {
                "Wed": [
                    {
                        "start": "14:00",
                        "end": "17:00"
                    }
                ],
                "Tue": [
                    {
                        "start": "18:00",
                        "end": "21:00"
                    }
                ]
            }
        },
        "K-E15-G027": {
            "name": "Quadrangle G027",
            "1": {
                "Wed": [
                    {
                        "start": "15:00",
                        "end": "18:00"
                    }
                ]
            },
            "2": {
                "Wed": [
                    {
                        "start": "15:00",
                        "end": "18:00"
                    }
                ]
            },
            "3": {
                "Wed": [
                    {
                        "start": "15:00",
                        "end": "18:00"
                    }
                ]
            },
            "4": {
                "Wed": [
                    {
                        "start": "15:00",
                        "end": "18:00"
                    }
                ]
            },
            "5": {
                "Wed": [
                    {
                        "start": "15:00",
                        "end": "18:00"
                    }
                ]
            },
            "6": {
                "Wed": [
                    {
                        "start": "15:00",
                        "end": "18:00"
                    }
                ]
            },
            "7": {
                "Wed": [
                    {
                        "start": "15:00",
                        "end": "18:00"
                    }
                ]
            },
            "8": {
                "Wed": [
                    {
                        "start": "15:00",
                        "end": "18:00"
                    }
                ]
            },
            "9": {
                "Wed": [
                    {
                        "start": "15:00",
                        "end": "18:00"
                    }
                ]
            },
            "10": {
                "Wed": [
                    {
                        "start": "15:00",
                        "end": "18:00"
                    }
                ]
            }
        }
    },
    "T2": {
        "termStart": "30/05/2022",
        "K-G17-G22": {
            "name": "Electrical Engineering G22",
            "1": {
                "Tue": [
                    {
                        "start": "14:00",
                        "end": "16:00"
                    }
                ]
            },
            "2": {
                "Tue": [
                    {
                        "start": "14:00",
                        "end": "16:00"
                    }
                ]
            },
            "3": {
                "Tue": [
                    {
                        "start": "14:00",
                        "end": "16:00"
                    }
                ]
            },
            "4": {
                "Tue": [
                    {
                        "start": "14:00",
                        "end": "16:00"
                    }
                ]
            },
            "5": {
                "Tue": [
                    {
                        "start": "14:00",
                        "end": "16:00"
                    }
                ]
            },
            "7": {
                "Tue": [
                    {
                        "start": "14:00",
                        "end": "16:00"
                    }
                ]
            },
            "8": {
                "Tue": [
                    {
                        "start": "14:00",
                        "end": "16:00"
                    }
                ]
            },
            "9": {
                "Tue": [
                    {
                        "start": "14:00",
                        "end": "16:00"
                    }
                ]
            },
            "10": {
                "Tue": [
                    {
                        "start": "14:00",
                        "end": "16:00"
                    }
                ]
            }
        },
        "K-E15-G027": {
            "name": "Quadrangle G027",
            "2": {
                "Tue": [
                    {
                        "start": "18:00",
                        "end": "19:30"
                    }
                ],
                "Wed": [
                    {
                        "start": "13:00",
                        "end": "14:30"
                    },
                    {
                        "start": "14:30",
                        "end": "16:00"
                    }
                ]
            },
            "3": {
                "Tue": [
                    {
                        "start": "18:00",
                        "end": "19:30"
                    }
                ],
                "Wed": [
                    {
                        "start": "13:00",
                        "end": "14:30"
                    },
                    {
                        "start": "14:30",
                        "end": "16:00"
                    }
                ]
            },
            "4": {
                "Tue": [
                    {
                        "start": "18:00",
                        "end": "19:30"
                    }
                ],
                "Wed": [
                    {
                        "start": "13:00",
                        "end": "14:30"
                    },
                    {
                        "start": "14:30",
                        "end": "16:00"
                    }
                ]
            },
            "5": {
                "Tue": [
                    {
                        "start": "18:00",
                        "end": "19:30"
                    }
                ],
                "Wed": [
                    {
                        "start": "13:00",
                        "end": "14:30"
                    },
                    {
                        "start": "14:30",
                        "end": "16:00"
                    }
                ]
            },
            "7": {
                "Tue": [
                    {
                        "start": "18:00",
                        "end": "19:30"
                    }
                ],
                "Wed": [
                    {
                        "start": "13:00",
                        "end": "14:30"
                    },
                    {
                        "start": "14:30",
                        "end": "16:00"
                    }
                ]
            },
            "8": {
                "Tue": [
                    {
                        "start": "18:00",
                        "end": "19:30"
                    }
                ],
                "Wed": [
                    {
                        "start": "13:00",
                        "end": "14:30"
                    },
                    {
                        "start": "14:30",
                        "end": "16:00"
                    }
                ]
            },
            "9": {
                "Tue": [
                    {
                        "start": "18:00",
                        "end": "19:30"
                    }
                ],
                "Wed": [
                    {
                        "start": "13:00",
                        "end": "14:30"
                    },
                    {
                        "start": "14:30",
                        "end": "16:00"
                    }
                ]
            },
            "10": {
                "Tue": [
                    {
                        "start": "18:00",
                        "end": "19:30"
                    }
                ],
                "Wed": [
                    {
                        "start": "13:00",
                        "end": "14:30"
                    },
                    {
                        "start": "14:30",
                        "end": "16:00"
                    }
                ]
            }
        },
        "K-C24-G17": {
            "name": "Sir John Clancy Auditorium",
            "1": {
                "Wed": [
                    {
                        "start": "13:00",
                        "end": "15:00"
                    }
                ]
            },
            "2": {
                "Wed": [
                    {
                        "start": "13:00",
                        "end": "15:00"
                    }
                ]
            },
            "3": {
                "Wed": [
                    {
                        "start": "13:00",
                        "end": "15:00"
                    }
                ]
            },
            "4": {
                "Wed": [
                    {
                        "start": "13:00",
                        "end": "15:00"
                    }
                ]
            },
            "5": {
                "Wed": [
                    {
                        "start": "13:00",
                        "end": "15:00"
                    }
                ]
            },
            "7": {
                "Wed": [
                    {
                        "start": "13:00",
                        "end": "15:00"
                    }
                ]
            },
            "8": {
                "Wed": [
                    {
                        "start": "13:00",
                        "end": "15:00"
                    }
                ]
            },
            "9": {
                "Wed": [
                    {
                        "start": "13:00",
                        "end": "15:00"
                    }
                ]
            },
            "10": {
                "Wed": [
                    {
                        "start": "13:00",
                        "end": "15:00"
                    }
                ]
            }
        },
        "K-G6-G13": {
            "name": "Blockhouse G13",
            "1": {
                "Thu": [
                    {
                        "start": "09:00",
                        "end": "10:30"
                    },
                    {
                        "start": "10:30",
                        "end": "12:00"
                    }
                ],
                "Tue": [
                    {
                        "start": "13:30",
                        "end": "15:00"
                    }
                ],
                "Wed": [
                    {
                        "start": "09:00",
                        "end": "10:30"
                    },
                    {
                        "start": "10:30",
                        "end": "12:00"
                    }
                ]
            },
            "2": {
                "Thu": [
                    {
                        "start": "09:00",
                        "end": "10:30"
                    },
                    {
                        "start": "10:30",
                        "end": "12:00"
                    }
                ],
                "Tue": [
                    {
                        "start": "13:30",
                        "end": "15:00"
                    }
                ],
                "Wed": [
                    {
                        "start": "09:00",
                        "end": "10:30"
                    },
                    {
                        "start": "10:30",
                        "end": "12:00"
                    }
                ]
            },
            "3": {
                "Thu": [
                    {
                        "start": "09:00",
                        "end": "10:30"
                    },
                    {
                        "start": "10:30",
                        "end": "12:00"
                    }
                ],
                "Tue": [
                    {
                        "start": "13:30",
                        "end": "15:00"
                    }
                ],
                "Wed": [
                    {
                        "start": "09:00",
                        "end": "10:30"
                    },
                    {
                        "start": "10:30",
                        "end": "12:00"
                    }
                ]
            },
            "4": {
                "Thu": [
                    {
                        "start": "09:00",
                        "end": "10:30"
                    },
                    {
                        "start": "10:30",
                        "end": "12:00"
                    }
                ],
                "Tue": [
                    {
                        "start": "13:30",
                        "end": "15:00"
                    }
                ],
                "Wed": [
                    {
                        "start": "09:00",
                        "end": "10:30"
                    },
                    {
                        "start": "10:30",
                        "end": "12:00"
                    }
                ]
            },
            "5": {
                "Thu": [
                    {
                        "start": "09:00",
                        "end": "10:30"
                    },
                    {
                        "start": "10:30",
                        "end": "12:00"
                    }
                ],
                "Tue": [
                    {
                        "start": "13:30",
                        "end": "15:00"
                    }
                ],
                "Wed": [
                    {
                        "start": "09:00",
                        "end": "10:30"
                    },
                    {
                        "start": "10:30",
                        "end": "12:00"
                    }
                ]
            },
            "7": {
                "Thu": [
                    {
                        "start": "09:00",
                        "end": "10:30"
                    },
                    {
                        "start": "10:30",
                        "end": "12:00"
                    }
                ],
                "Tue": [
                    {
                        "start": "13:30",
                        "end": "15:00"
                    }
                ],
                "Wed": [
                    {
                        "start": "09:00",
                        "end": "10:30"
                    },
                    {
                        "start": "10:30",
                        "end": "12:00"
                    }
                ]
            },
            "8": {
                "Thu": [
                    {
                        "start": "09:00",
                        "end": "10:30"
                    },
                    {
                        "start": "10:30",
                        "end": "12:00"
                    }
                ],
                "Tue": [
                    {
                        "start": "13:30",
                        "end": "15:00"
                    }
                ],
                "Wed": [
                    {
                        "start": "09:00",
                        "end": "10:30"
                    },
                    {
                        "start": "10:30",
                        "end": "12:00"
                    }
                ]
            },
            "9": {
                "Thu": [
                    {
                        "start": "09:00",
                        "end": "10:30"
                    },
                    {
                        "start": "10:30",
                        "end": "12:00"
                    }
                ],
                "Tue": [
                    {
                        "start": "13:30",
                        "end": "15:00"
                    }
                ],
                "Wed": [
                    {
                        "start": "09:00",
                        "end": "10:30"
                    },
                    {
                        "start": "10:30",
                        "end": "12:00"
                    }
                ]
            },
            "10": {
                "Thu": [
                    {
                        "start": "09:00",
                        "end": "10:30"
                    },
                    {
                        "start": "10:30",
                        "end": "12:00"
                    }
                ],
                "Tue": [
                    {
                        "start": "13:30",
                        "end": "15:00"
                    }
                ],
                "Wed": [
                    {
                        "start": "09:00",
                        "end": "10:30"
                    },
                    {
                        "start": "10:30",
                        "end": "12:00"
                    }
                ]
            }
        },
        "K-G6-G14": {
            "name": "Blockhouse G14",
            "1": {
                "Tue": [
                    {
                        "start": "12:00",
                        "end": "13:30"
                    },
                    {
                        "start": "13:30",
                        "end": "15:00"
                    }
                ],
                "Wed": [
                    {
                        "start": "10:30",
                        "end": "12:00"
                    }
                ]
            },
            "2": {
                "Tue": [
                    {
                        "start": "12:00",
                        "end": "13:30"
                    },
                    {
                        "start": "13:30",
                        "end": "15:00"
                    }
                ],
                "Wed": [
                    {
                        "start": "10:30",
                        "end": "12:00"
                    }
                ]
            },
            "3": {
                "Tue": [
                    {
                        "start": "12:00",
                        "end": "13:30"
                    },
                    {
                        "start": "13:30",
                        "end": "15:00"
                    }
                ],
                "Wed": [
                    {
                        "start": "10:30",
                        "end": "12:00"
                    }
                ]
            },
            "4": {
                "Tue": [
                    {
                        "start": "12:00",
                        "end": "13:30"
                    },
                    {
                        "start": "13:30",
                        "end": "15:00"
                    }
                ],
                "Wed": [
                    {
                        "start": "10:30",
                        "end": "12:00"
                    }
                ]
            },
            "5": {
                "Tue": [
                    {
                        "start": "12:00",
                        "end": "13:30"
                    },
                    {
                        "start": "13:30",
                        "end": "15:00"
                    }
                ],
                "Wed": [
                    {
                        "start": "10:30",
                        "end": "12:00"
                    }
                ]
            },
            "7": {
                "Tue": [
                    {
                        "start": "12:00",
                        "end": "13:30"
                    },
                    {
                        "start": "13:30",
                        "end": "15:00"
                    }
                ],
                "Wed": [
                    {
                        "start": "10:30",
                        "end": "12:00"
                    }
                ]
            },
            "8": {
                "Tue": [
                    {
                        "start": "12:00",
                        "end": "13:30"
                    },
                    {
                        "start": "13:30",
                        "end": "15:00"
                    }
                ],
                "Wed": [
                    {
                        "start": "10:30",
                        "end": "12:00"
                    }
                ]
            },
            "9": {
                "Tue": [
                    {
                        "start": "12:00",
                        "end": "13:30"
                    },
                    {
                        "start": "13:30",
                        "end": "15:00"
                    }
                ],
                "Wed": [
                    {
                        "start": "10:30",
                        "end": "12:00"
                    }
                ]
            },
            "10": {
                "Tue": [
                    {
                        "start": "12:00",
                        "end": "13:30"
                    },
                    {
                        "start": "13:30",
                        "end": "15:00"
                    }
                ],
                "Wed": [
                    {
                        "start": "10:30",
                        "end": "12:00"
                    }
                ]
            }
        },
        "K-F23-308": {
            "name": "Mathews  308",
            "1": {
                "Wed": [
                    {
                        "start": "15:00",
                        "end": "16:30"
                    },
                    {
                        "start": "18:00",
                        "end": "19:30"
                    }
                ]
            },
            "2": {
                "Wed": [
                    {
                        "start": "15:00",
                        "end": "16:30"
                    },
                    {
                        "start": "18:00",
                        "end": "19:30"
                    }
                ]
            },
            "3": {
                "Wed": [
                    {
                        "start": "15:00",
                        "end": "16:30"
                    },
                    {
                        "start": "18:00",
                        "end": "19:30"
                    }
                ]
            },
            "4": {
                "Wed": [
                    {
                        "start": "15:00",
                        "end": "16:30"
                    },
                    {
                        "start": "18:00",
                        "end": "19:30"
                    }
                ]
            },
            "5": {
                "Wed": [
                    {
                        "start": "15:00",
                        "end": "16:30"
                    },
                    {
                        "start": "18:00",
                        "end": "19:30"
                    }
                ]
            },
            "7": {
                "Wed": [
                    {
                        "start": "15:00",
                        "end": "16:30"
                    },
                    {
                        "start": "18:00",
                        "end": "19:30"
                    }
                ]
            },
            "8": {
                "Wed": [
                    {
                        "start": "15:00",
                        "end": "16:30"
                    },
                    {
                        "start": "18:00",
                        "end": "19:30"
                    }
                ]
            },
            "9": {
                "Wed": [
                    {
                        "start": "15:00",
                        "end": "16:30"
                    },
                    {
                        "start": "18:00",
                        "end": "19:30"
                    }
                ]
            },
            "10": {
                "Wed": [
                    {
                        "start": "15:00",
                        "end": "16:30"
                    },
                    {
                        "start": "18:00",
                        "end": "19:30"
                    }
                ]
            }
        },
        "K-E12-220": {
            "name": "UNSW Business School  220",
            "1": {
                "Wed": [
                    {
                        "start": "14:00",
                        "end": "17:00"
                    }
                ],
                "Thu": [
                    {
                        "start": "10:00",
                        "end": "13:00"
                    }
                ],
                "Mon": [
                    {
                        "start": "14:00",
                        "end": "17:00"
                    }
                ]
            },
            "2": {
                "Wed": [
                    {
                        "start": "14:00",
                        "end": "17:00"
                    }
                ],
                "Thu": [
                    {
                        "start": "10:00",
                        "end": "13:00"
                    }
                ],
                "Mon": [
                    {
                        "start": "14:00",
                        "end": "17:00"
                    }
                ]
            },
            "3": {
                "Wed": [
                    {
                        "start": "14:00",
                        "end": "17:00"
                    }
                ],
                "Thu": [
                    {
                        "start": "10:00",
                        "end": "13:00"
                    }
                ]
            },
            "4": {
                "Wed": [
                    {
                        "start": "14:00",
                        "end": "17:00"
                    }
                ],
                "Thu": [
                    {
                        "start": "10:00",
                        "end": "13:00"
                    }
                ],
                "Mon": [
                    {
                        "start": "14:00",
                        "end": "17:00"
                    }
                ]
            },
            "5": {
                "Wed": [
                    {
                        "start": "14:00",
                        "end": "17:00"
                    }
                ],
                "Thu": [
                    {
                        "start": "10:00",
                        "end": "13:00"
                    }
                ],
                "Mon": [
                    {
                        "start": "14:00",
                        "end": "17:00"
                    }
                ]
            },
            "7": {
                "Wed": [
                    {
                        "start": "14:00",
                        "end": "17:00"
                    }
                ],
                "Thu": [
                    {
                        "start": "10:00",
                        "end": "13:00"
                    }
                ],
                "Mon": [
                    {
                        "start": "14:00",
                        "end": "17:00"
                    }
                ]
            },
            "8": {
                "Wed": [
                    {
                        "start": "14:00",
                        "end": "17:00"
                    }
                ],
                "Thu": [
                    {
                        "start": "10:00",
                        "end": "13:00"
                    }
                ],
                "Mon": [
                    {
                        "start": "14:00",
                        "end": "17:00"
                    }
                ]
            },
            "9": {
                "Wed": [
                    {
                        "start": "14:00",
                        "end": "17:00"
                    }
                ],
                "Thu": [
                    {
                        "start": "10:00",
                        "end": "13:00"
                    }
                ],
                "Mon": [
                    {
                        "start": "14:00",
                        "end": "17:00"
                    }
                ]
            },
            "10": {
                "Wed": [
                    {
                        "start": "14:00",
                        "end": "17:00"
                    }
                ],
                "Thu": [
                    {
                        "start": "10:00",
                        "end": "13:00"
                    }
                ],
                "Mon": [
                    {
                        "start": "14:00",
                        "end": "17:00"
                    }
                ]
            },
            "6": {
                "Thu": [
                    {
                        "start": "10:00",
                        "end": "13:00"
                    }
                ],
                "Mon": [
                    {
                        "start": "14:00",
                        "end": "17:00"
                    }
                ]
            }
        },
        "K-E12-119": {
            "name": "UNSW Business School 119",
            "1": {
                "Wed": [
                    {
                        "start": "14:00",
                        "end": "17:00"
                    }
                ]
            },
            "2": {
                "Wed": [
                    {
                        "start": "14:00",
                        "end": "17:00"
                    }
                ]
            },
            "3": {
                "Wed": [
                    {
                        "start": "14:00",
                        "end": "17:00"
                    }
                ]
            },
            "4": {
                "Wed": [
                    {
                        "start": "14:00",
                        "end": "17:00"
                    }
                ]
            },
            "5": {
                "Wed": [
                    {
                        "start": "14:00",
                        "end": "17:00"
                    }
                ]
            },
            "6": {
                "Wed": [
                    {
                        "start": "14:00",
                        "end": "17:00"
                    }
                ]
            },
            "7": {
                "Wed": [
                    {
                        "start": "14:00",
                        "end": "17:00"
                    }
                ]
            },
            "8": {
                "Wed": [
                    {
                        "start": "14:00",
                        "end": "17:00"
                    }
                ]
            },
            "9": {
                "Wed": [
                    {
                        "start": "14:00",
                        "end": "17:00"
                    }
                ]
            },
            "10": {
                "Wed": [
                    {
                        "start": "14:00",
                        "end": "17:00"
                    }
                ]
            }
        },
        "K-J17-G03": {
            "name": "Ainsworth G03",
            "1": {
                "Wed": [
                    {
                        "start": "18:00",
                        "end": "21:00"
                    }
                ]
            },
            "2": {
                "Wed": [
                    {
                        "start": "18:00",
                        "end": "21:00"
                    }
                ]
            },
            "3": {
                "Wed": [
                    {
                        "start": "18:00",
                        "end": "21:00"
                    }
                ]
            },
            "4": {
                "Wed": [
                    {
                        "start": "18:00",
                        "end": "21:00"
                    }
                ]
            },
            "5": {
                "Wed": [
                    {
                        "start": "18:00",
                        "end": "21:00"
                    }
                ]
            },
            "6": {
                "Wed": [
                    {
                        "start": "18:00",
                        "end": "21:00"
                    }
                ]
            },
            "7": {
                "Wed": [
                    {
                        "start": "18:00",
                        "end": "21:00"
                    }
                ]
            },
            "8": {
                "Wed": [
                    {
                        "start": "18:00",
                        "end": "21:00"
                    }
                ]
            },
            "9": {
                "Wed": [
                    {
                        "start": "18:00",
                        "end": "21:00"
                    }
                ]
            },
            "10": {
                "Wed": [
                    {
                        "start": "18:00",
                        "end": "21:00"
                    }
                ]
            }
        },
        "K-F23-228": {
            "name": "Mathews 228",
            "1": {
                "Fri": [
                    {
                        "start": "10:00",
                        "end": "13:00"
                    }
                ]
            },
            "2": {
                "Fri": [
                    {
                        "start": "10:00",
                        "end": "13:00"
                    }
                ]
            },
            "3": {
                "Fri": [
                    {
                        "start": "10:00",
                        "end": "13:00"
                    }
                ]
            },
            "4": {
                "Fri": [
                    {
                        "start": "10:00",
                        "end": "13:00"
                    }
                ]
            },
            "5": {
                "Fri": [
                    {
                        "start": "10:00",
                        "end": "13:00"
                    }
                ]
            },
            "6": {
                "Fri": [
                    {
                        "start": "10:00",
                        "end": "13:00"
                    }
                ]
            },
            "7": {
                "Fri": [
                    {
                        "start": "10:00",
                        "end": "13:00"
                    }
                ]
            },
            "8": {
                "Fri": [
                    {
                        "start": "10:00",
                        "end": "13:00"
                    }
                ]
            },
            "9": {
                "Fri": [
                    {
                        "start": "10:00",
                        "end": "13:00"
                    }
                ]
            },
            "10": {
                "Fri": [
                    {
                        "start": "10:00",
                        "end": "13:00"
                    }
                ]
            }
        }
    },
    "T3": {
        "termStart": "12/09/2022"
    }
}